<Properties StartupConfiguration="{EA257311-6346-4B0D-B4C9-5CCB77675063}|https">
  <MonoDevelop.Ide.DebuggingService.PinnedWatches />
  <MonoDevelop.Ide.Workspace ActiveConfiguration="Debug" />
  <MonoDevelop.Ide.Workbench>
    <Pads>
      <Pad Id="ProjectPad">
        <State name="__root__">
          <Node name="FindYourRecipe" expanded="True" selected="True" />
        </State>
      </Pad>
    </Pads>
  </MonoDevelop.Ide.Workbench>
  <MonoDevelop.Ide.DebuggingService.Breakpoints />
  <MultiItemStartupConfigurations />
  <MonoDevelop.Ide.ItemProperties.FindYourRecipe.Api PreferredExecutionTarget="/Applications/Google Chrome.app" />
  <MonoDevelop.Ide.ItemProperties.FindYourRecipe.DataAccess FirstBuild="True" />
</Properties>